sz_calculator/__init__.py
sz_calculator/__main__.py
sz_calculator/calc.py
sz_calculator-0.0.1.dist-info/METADATA
sz_calculator-0.0.1.dist-info/WHEEL
sz_calculator-0.0.1.dist-info/entry_points.txt
sz_calculator-0.0.1.dist-info/top_level.txt
sz_calculator-0.0.1.dist-info/RECORD
