Metadata-Version: 2.1
Name: sz-calculator
Version: 0.0.1
Summary: Cool Calculator
Home-page: https://github.com/stonezhong/pythondemos/tree/master/sz_calculator
Author: Stone Zhong
Author-email: stonezhong@hotmail.com
License: MIT
Platform: UNKNOWN
Classifier: License :: OSI Approved :: MIT License
Classifier: Programming Language :: Python :: 3
Classifier: Programming Language :: Python :: 3.6
